{"__collections__":{"historial":{"ea0ARctfE2VjZw1JyZAv":{"fecha":"2025-07-19","servicio":"Oración y Enseñanza","ujier":"Juan Caldera","hermanos":5,"hermanas":6,"ninos":5,"adolescentes":5,"simpatizantes":4,"simpatizantesAsistieron":[],"miembrosAsistieron":{"hermanos":[],"hermanas":[],"ninos":[],"adolescentes":[]},"total":25,"__collections__":{}},"exeZEyHX2aXins9CI8NY":{"fecha":"2025-07-19","servicio":"Dominical","ujier":"Joaquin Velez","hermanos":4,"hermanas":5,"ninos":5,"adolescentes":4,"simpatizantes":3,"simpatizantesAsistieron":[],"miembrosAsistieron":{"hermanos":[],"hermanas":[],"ninos":[],"adolescentes":[]},"total":21,"__collections__":{}}},"miembros":{"1ixWLDAMyPq1MPJA4vP5":{"nombre":"Marbel","telefono":"","categoria":"hermana","notas":"","fechaRegistro":"2025-07-19","__collections__":{}},"1nA5WQSs1um7q5gagwO2":{"nombre":"Nicol Henao","telefono":"","categoria":"hermana","notas":"","fechaRegistro":"2025-07-19","__collections__":{}},"23JHG6kRmdthU2CkZHSg":{"nombre":"Estella","telefono":"","categoria":"hermana","notas":"","fechaRegistro":"2025-07-19","__collections__":{}},"37DTQcPNmkqbETbMRnGn":{"nombre":"Jenny","telefono":"","notas":"","fechaRegistro":"2025-07-19","categoria":"hermana","__collections__":{}},"3IEGlcwsqB1yqBlPHjRG":{"nombre":"Geraldo Restrepo","telefono":"","categoria":"hermano","notas":"","fechaRegistro":"2025-07-19","__collections__":{}},"3y5oIeHmBUM6MR8BjWAT":{"nombre":"Jhojana Giraldo","telefono":"","categoria":"hermana","notas":"","fechaRegistro":"2025-07-19","__collections__":{}},"5bD8JoX3cYS3hJ95qhT9":{"nombre":"Josue","telefono":"","categoria":"hermano","notas":"","fechaRegistro":"2025-07-19","__collections__":{}},"8E32VtVJXbH1ENspSFep":{"nombre":"Lucia Gomez","telefono":"","categoria":"hermana","notas":"","fechaRegistro":"2025-07-19","__collections__":{}},"8M8e2Df63KgIrj1beyst":{"nombre":"Yojan","telefono":"","categoria":"hermano","notas":"","fechaRegistro":"2025-07-19","__collections__":{}},"ARLBVDFhXA9UF07A8WEs":{"nombre":"Nelly","telefono":"","categoria":"hermana","notas":"","fechaRegistro":"2025-07-19","__collections__":{}},"CnN7RXWLHg33lSMWHncq":{"nombre":"Oraliz","telefono":"","categoria":"hermana","notas":"","fechaRegistro":"2025-07-19","__collections__":{}},"DTfMsn7e9ymGQdfX2ChV":{"nombre":"Wilmar Velez","telefono":"","categoria":"hermano","notas":"","fechaRegistro":"2025-07-19","__collections__":{}},"DZhgs7bRHlctBcCRT98I":{"nombre":"Doris Delgado","telefono":"","categoria":"hermana","notas":"","fechaRegistro":"2025-07-19","__collections__":{}},"DdPbzo3aGKhDqfMJmxys":{"nombre":"Evelin","telefono":"","notas":"","fechaRegistro":"2025-07-19","categoria":"hermana","__collections__":{}},"DkscS3X0tCztEwOnuoHM":{"nombre":"Marina Parra ","telefono":"","categoria":"hermana","notas":"","fechaRegistro":"2025-07-19","__collections__":{}},"EXUdV1j3SPnWVmVV92ns":{"nombre":"Nuvia","telefono":"","categoria":"hermana","notas":"","fechaRegistro":"2025-07-19","__collections__":{}},"FWDHVjZEvsU36DDcOSyV":{"nombre":"Carolina Monzalve","telefono":"","categoria":"hermana","notas":"","fechaRegistro":"2025-07-19","__collections__":{}},"JeqRBHvz4NiFVY7HuC5e":{"nombre":"Alejo Henao","telefono":"","categoria":"hermano","notas":"","fechaRegistro":"2025-07-19","__collections__":{}},"KNaIebAKma4QJd9JFptX":{"nombre":"Willy Hincapie","telefono":"","categoria":"hermano","notas":"","fechaRegistro":"2025-07-19","__collections__":{}},"KnPcLYlHmdXwBgrQQDWr":{"nombre":"Hector Gaviria","telefono":"","categoria":"hermano","notas":"","fechaRegistro":"2025-07-19","__collections__":{}},"LGfpkjraOW18oD9YC9mo":{"nombre":"Cristian Gomez Velez","telefono":"","categoria":"hermano","notas":"","fechaRegistro":"2025-07-19","__collections__":{}},"LKRtqrK442vqKovUh5Qj":{"nombre":"Diana Suarez","telefono":"","categoria":"hermana","notas":"","fechaRegistro":"2025-07-19","__collections__":{}},"LvGdq2OOoRYAt3bBJpqD":{"nombre":"Hector","telefono":"","categoria":"hermano","notas":"","fechaRegistro":"2025-07-19","__collections__":{}},"M2aWXuXgKguFrNQi4ZBs":{"nombre":"Catherine","telefono":"","categoria":"hermana","notas":"","fechaRegistro":"2025-07-19","__collections__":{}},"MmV8hzAEIGuaEqWakgi3":{"nombre":"Sarai Margarita Londoño Velez","telefono":"","categoria":"adolescente","notas":"","fechaRegistro":"2025-07-19","__collections__":{}},"NN56MCvLkMjw5MTdWgvw":{"nombre":"Julieth Correa","telefono":"","categoria":"hermana","notas":"","fechaRegistro":"2025-07-19","__collections__":{}},"NNpKhD66Oko9sZVu3KYy":{"nombre":"Martha Verona","telefono":"","categoria":"hermana","notas":"","fechaRegistro":"2025-07-19","__collections__":{}},"OUlzIbFwo0rUHZThvZbB":{"nombre":"Maria Elena","telefono":"","categoria":"hermana","notas":"","fechaRegistro":"2025-07-19","__collections__":{}},"PKgFHpt002fxUBZbsai6":{"nombre":"Fernando Arias","telefono":"","categoria":"hermano","notas":"","fechaRegistro":"2025-07-19","__collections__":{}},"R7GVjOfCjZfq2iDMlBLq":{"nombre":"Hector Alzate Ortiz","telefono":"","categoria":"hermano","notas":"","fechaRegistro":"2025-07-19","__collections__":{}},"RkJTpRiz7dCysqNA5hTf":{"nombre":"Yariza","telefono":"","categoria":"hermana","notas":"","fechaRegistro":"2025-07-19","__collections__":{}},"SLzfRQCyUOepuMQlnDgw":{"nombre":"Yury","telefono":"","categoria":"hermana","notas":"","fechaRegistro":"2025-07-19","__collections__":{}},"VFNpycuZHbHMTjJCYvPD":{"nombre":"Tiberio","telefono":"","categoria":"hermano","notas":"","fechaRegistro":"2025-07-19","__collections__":{}},"VoRlOINtRUsCeAQ31UUC":{"nombre":"Yamile","telefono":"","categoria":"hermana","notas":"","fechaRegistro":"2025-07-19","__collections__":{}},"WzwgpcVTK5tzrs5l5CtL":{"nombre":"Sury Maribel Velez Parra","telefono":"","categoria":"hermana","notas":"","fechaRegistro":"2025-07-19","__collections__":{}},"XFu3SQoFUdvXANuywLNB":{"nombre":"Ivan Caro","telefono":"","categoria":"hermano","notas":"","fechaRegistro":"2025-07-19","__collections__":{}},"XeHN6ixJ3lFmUvjgK5uc":{"nombre":"Nicolas Gomez Velez","telefono":"3046619628","categoria":"hermano","notas":"","fechaRegistro":"2025-07-19","__collections__":{}},"Ye9svdD5Jl9KRbUn2jkO":{"nombre":"Dora Vergara","telefono":"","categoria":"hermana","notas":"","fechaRegistro":"2025-07-19","__collections__":{}},"YoyIh5bqpJSopkEka5EE":{"nombre":"Gilberto Castaño (Pastor)","telefono":"","categoria":"hermano","notas":"","fechaRegistro":"2025-07-19","__collections__":{}},"ZQj6CN0eYuknP6Lga2kF":{"nombre":"Karen","telefono":"","categoria":"hermana","notas":"","fechaRegistro":"2025-07-19","__collections__":{}},"ZQliERM49b5sj1hLEUXc":{"nombre":"Clara","telefono":"","categoria":"hermana","notas":"","fechaRegistro":"2025-07-19","__collections__":{}},"b7yd3gONKqebdJGjF1pF":{"nombre":"Lili","telefono":"","categoria":"hermana","notas":"","fechaRegistro":"2025-07-19","__collections__":{}},"eSAK2aFf2mfpu0UE84xr":{"nombre":"Patricia","telefono":"","categoria":"hermana","notas":"","fechaRegistro":"2025-07-19","__collections__":{}},"es7WMnToubRLJSzYBcyL":{"telefono":"","categoria":"hermano","notas":"","fechaRegistro":"2025-07-19","nombre":"Johan Henao","__collections__":{}},"fDVwgfOTf5Fej5kI5Jla":{"nombre":"Diana Velez","telefono":"","categoria":"hermana","notas":"","fechaRegistro":"2025-07-19","__collections__":{}},"fyxbQnyBQ3yuz11Qj2eg":{"nombre":"Elvia Ruiz","telefono":"","categoria":"hermana","notas":"","fechaRegistro":"2025-07-19","__collections__":{}},"hj24uBNkrMbXLJCX2ODc":{"nombre":"Sonia Osorio","telefono":"","categoria":"hermana","notas":"","fechaRegistro":"2025-07-19","__collections__":{}},"hrl1iBCRtlG6OahhzQ4v":{"nombre":"Beatriz Suarez","telefono":"","categoria":"hermana","notas":"","fechaRegistro":"2025-07-19","__collections__":{}},"kQTx66FErEVFmM8fcjPb":{"nombre":"Jhon Echavarria","telefono":"","categoria":"hermano","notas":"","fechaRegistro":"2025-07-19","__collections__":{}},"lPqxtQ5302Pi1FWHelEI":{"nombre":"Juan Caldera","telefono":"","categoria":"hermano","notas":"","fechaRegistro":"2025-07-19","__collections__":{}},"lukUmVuOBya2qjLxyR62":{"nombre":"Dina","telefono":"","categoria":"hermana","notas":"","fechaRegistro":"2025-07-19","__collections__":{}},"nVUdRrKc5JtaeWYcRTxz":{"nombre":"Sebastian","telefono":"","categoria":"hermano","notas":"","fechaRegistro":"2025-07-19","__collections__":{}},"nqEbTQumTZT37sMscWNE":{"nombre":"ESteban","telefono":"","categoria":"hermano","notas":"","fechaRegistro":"2025-07-19","__collections__":{}},"pyJTumu2pXX7eVyg0tYT":{"nombre":"Juan Jose Avendaño Velez","telefono":"","categoria":"hermano","notas":"","fechaRegistro":"2025-07-19","__collections__":{}},"q5cSOV1ygrrCkbK6sM2m":{"nombre":"Sandra ","telefono":"","categoria":"hermana","notas":"","fechaRegistro":"2025-07-19","__collections__":{}},"r0HiJ1jd17hVoXeQNBDf":{"nombre":"Juan Monsalve","telefono":"","categoria":"hermano","notas":"","fechaRegistro":"2025-07-19","__collections__":{}},"riurM4XTNIinChGXguna":{"nombre":"Natlaia","telefono":"","categoria":"hermana","notas":"","fechaRegistro":"2025-07-19","__collections__":{}},"tCXrTwwq2a9u9eUwDChV":{"nombre":"Juan Diego Ramirez","telefono":"","categoria":"hermano","notas":"","fechaRegistro":"2025-07-19","__collections__":{}},"uVbedU4JmWePUbmO4IX5":{"nombre":"John Fredy Ramirez","telefono":"","categoria":"hermano","notas":"","fechaRegistro":"2025-07-19","__collections__":{}},"wAohxiiFFqjos0jpHZ4W":{"nombre":"Wilmar Rojas","telefono":"","categoria":"hermano","notas":"","fechaRegistro":"2025-07-19","__collections__":{}},"yR57UMEHArnNCxj7G3d9":{"nombre":"Carmen","telefono":"","categoria":"hermana","notas":"","fechaRegistro":"2025-07-19","__collections__":{}}},"simpatizantes":{"81LGlvTNGSgoxqE0Kx1W":{"nombre":"Leidy","telefono":"","notas":"","fechaRegistro":"2025-07-19","__collections__":{}},"BNJpHFoxTQy6LPhAWjku":{"nombre":"Marissa Martinez","telefono":"","notas":"","fechaRegistro":"2025-07-19","__collections__":{}},"MhAhjQcGRsXE8HfLs5Ik":{"nombre":"Yessica","telefono":"","notas":"","fechaRegistro":"2025-07-19","__collections__":{}},"WLK59J1UnLPKSPrWkomY":{"nombre":"Oscar Isaza","telefono":"","notas":"","fechaRegistro":"2025-07-19","__collections__":{}},"Zeu5BlAXKTfILqtxj8r8":{"nombre":"Tiago Martinez","telefono":"","notas":"","fechaRegistro":"2025-07-19","__collections__":{}},"f4X4bb4eqLicslC7pHxl":{"nombre":"Sergio Peña","telefono":"","notas":"Alto","fechaRegistro":"2025-07-19","__collections__":{}},"gFe6IxMSWJufa64ltyDS":{"nombre":"Piedad Piedrahita","telefono":"","notas":"","fechaRegistro":"2025-07-19","__collections__":{}},"okrJGOuMzWyOSu7a4pEC":{"nombre":"Eugenia Delas Aguas","telefono":"","notas":"","fechaRegistro":"2025-07-19","__collections__":{}},"uZOUJvUcvZTcma2KRwce":{"nombre":"Michel","telefono":"","notas":"","fechaRegistro":"2025-07-19","__collections__":{}}}}}